outliers/__init__.py
outliers/smirnov_grubbs.py
outlier_utils-0.0.5.dist-info/LICENSE
outlier_utils-0.0.5.dist-info/METADATA
outlier_utils-0.0.5.dist-info/WHEEL
outlier_utils-0.0.5.dist-info/top_level.txt
outlier_utils-0.0.5.dist-info/RECORD
