Metadata-Version: 2.1
Name: outlier-utils
Version: 0.0.5
Summary: Utility library for detecting and removing outliers from normally distributed datasets
Author-email: Masashi Shibata <contact@c-bata.link>
License: MIT License
Project-URL: Homepage, https://github.com/c-bata/outlier-utils
Project-URL: Sources, https://github.com/c-bata/outlier-utils
Project-URL: Bug Tracker, https://github.com/c-bata/outlier-utils/issues
Classifier: Development Status :: 3 - Alpha
Classifier: Intended Audience :: Science/Research
Classifier: Topic :: Scientific/Engineering
Classifier: License :: OSI Approved :: MIT License
Classifier: Programming Language :: Python
Classifier: Programming Language :: Python :: 3
License-File: LICENSE
Requires-Dist: numpy
Requires-Dist: scipy
